mysharelib/__init__.py
mysharelib/blob_cache.py
mysharelib/em/__init__.py
mysharelib/em/get_a_info_em.py
mysharelib/em/get_hk_info_em.py
mysharelib/em/orginfo.py
mysharelib/em/stock_balance_sheet.py
mysharelib/em/stock_cash_flow_sheet.py
mysharelib/em/stock_hk_gdfx_em.py
mysharelib/em/stock_income_sheet.py
mysharelib/em/stock_info_em.py
mysharelib/em/stock_notice_em.py
mysharelib/em/stock_report_em.py
mysharelib/registry.py
mysharelib/sina/scrape_hk_stock_news.py
mysharelib/table_cache.py
mysharelib/tools.py
mysharelib-1.0.4.dist-info/METADATA
mysharelib-1.0.4.dist-info/WHEEL
mysharelib-1.0.4.dist-info/RECORD
