Metadata-Version: 2.3
Name: mysharelib
Version: 1.0.4
Summary: My share library
Author: Roger Ye
Author-email: shugaoye@yahoo.com
Requires-Python: >=3.11,<3.13
Classifier: Programming Language :: Python :: 3
Classifier: Programming Language :: Python :: 3.11
Classifier: Programming Language :: Python :: 3.12
Requires-Dist: akshare (>=1.17.38,<2.0.0)
Requires-Dist: chinese-calendar (>=1.10.0,<2.0.0)
Requires-Dist: openbb-core (>=1.4.8,<2.0.0)
